prutils/__init__.py
prutils/cmds.py
prutils/pr_dmhelper.py
prutils/pr_jinja2.py
prutils/pr_pilhelper.py
prutils/pr_requests.py
prutils/pr_string.py
prutils/pr_url.py
prutils/pr_utils.py
prutils-0.0.26.dist-info/LICENSE
prutils-0.0.26.dist-info/METADATA
prutils-0.0.26.dist-info/WHEEL
prutils-0.0.26.dist-info/entry_points.txt
prutils-0.0.26.dist-info/top_level.txt
prutils-0.0.26.dist-info/RECORD
